aiotaika/.gitignore
aiotaika/__init__.py
aiotaika/aiotaika.py
aiotaika/const.py
aiotaika/discovery.py
aiotaika/entity.py
aiotaika/errors.py
aiotaika/events.py
aiotaika/locator.py
aiotaika/mqtthandler.py
aiotaika/ring.py
aiotaika/utils.py
aiotaika-0.1.2.dist-info/AUTHORS.rst
aiotaika-0.1.2.dist-info/LICENSE
aiotaika-0.1.2.dist-info/METADATA
aiotaika-0.1.2.dist-info/WHEEL
aiotaika-0.1.2.dist-info/top_level.txt
aiotaika-0.1.2.dist-info/RECORD
