Metadata-Version: 2.1
Name: aiotaika
Version: 0.1.2
Summary: Taika asynchronous client library for Python
Author-email: Taika Tech Oy <dev@taikatech.fi>
Maintainer-email: Jussi Hietanen <jussi@taikatech.fi>
License: LGPL-2.1 license
Project-URL: Source code, https://github.com/Taika-Tech/aiotaika-python
Project-URL: Issue tracker, https://github.com/Taika-Tech/aiotaika-python/issues
Project-URL: Documentation, https://aiotaika-python.readthedocs.io
Keywords: async,asyncio,taika,client,iot
Classifier: Development Status :: 3 - Alpha
Classifier: Intended Audience :: Developers
Classifier: License :: OSI Approved
Classifier: Operating System :: POSIX :: Linux
Classifier: Operating System :: Microsoft :: Windows
Classifier: Operating System :: MacOS
Classifier: Programming Language :: Python :: 3
Classifier: Programming Language :: Python :: 3.8
Classifier: Programming Language :: Python :: 3.9
Classifier: Programming Language :: Python :: 3.10
Classifier: Programming Language :: Python :: 3.11
Classifier: Topic :: Software Development :: Libraries :: Python Modules
Requires-Python: >=3.8
License-File: LICENSE
License-File: AUTHORS.rst
Requires-Dist: aiomysql (>=0.1.1)
Requires-Dist: asyncio-mqtt (>=0.16.1)
Provides-Extra: docs
Requires-Dist: sphinx (>=5.3.0) ; extra == 'docs'
Requires-Dist: sphinx-rtd-theme (>=1.2.0) ; extra == 'docs'
Provides-Extra: format
Requires-Dist: black (>=23.3.0) ; extra == 'format'
Requires-Dist: flake8 (>=6.0.0) ; extra == 'format'
Requires-Dist: bandit (>=1.7.4) ; extra == 'format'
Requires-Dist: isort (>=5.12.0) ; extra == 'format'
Provides-Extra: lint
Requires-Dist: mypy (>=1.2.0) ; extra == 'lint'
Requires-Dist: ruff (==0.0.261) ; extra == 'lint'
Requires-Dist: markdownlint (>=0.12.0) ; extra == 'lint'
